<PubmedArticle>
    <MedlineCitation Owner="NLM" Status="MEDLINE">
        <PMID Version="1">16881566</PMID>
        <DateCreated>
            <Year>2006</Year>
            <Month>08</Month>
            <Day>02</Day>
        </DateCreated>
        <DateCompleted>
            <Year>2006</Year>
            <Month>09</Month>
            <Day>12</Day>
        </DateCompleted>
        <DateRevised>
            <Year>2014</Year>
            <Month>03</Month>
            <Day>18</Day>
        </DateRevised>
        <Article PubModel="Print">
            <Journal>
                <ISSN IssnType="Print">1784-3286</ISSN>
                <JournalIssue CitedMedium="Print">
                    <Volume>61</Volume>
                    <Issue>3</Issue>
                    <PubDate>
                        <MedlineDate>2006 May-Jun</MedlineDate>
                    </PubDate>
                </JournalIssue>
                <Title>Acta clinica Belgica</Title>
                <ISOAbbreviation>Acta Clin Belg</ISOAbbreviation>
            </Journal>
            <ArticleTitle>Coriander anaphylaxis in a spice grinder with undetected occupational allergy.</ArticleTitle>
            <Pagination>
                <MedlinePgn>152-6</MedlinePgn>
            </Pagination>
            <Abstract>
                <AbstractText Label="BACKGROUND" NlmCategory="BACKGROUND">Anaphylaxis after ingestion of spices as a result from occupational sensitization remains anecdotal. We describe a patient, working in a spice factory, with anaphylaxis from coriander in a meal. He also demonstrated urticaria, angio-edema, rhinoconjunctivitis and bronchospasm during handling coriander and fenugreek.</AbstractText>
                <AbstractText Label="OBJECTIVE" NlmCategory="OBJECTIVE">To determine the mechanism of the anaphylactic reaction and to evaluate cross-reactivity between both botanically unrelated spices.</AbstractText>
                <AbstractText Label="METHODS" NlmCategory="METHODS">Investigations comprised quantification of total and specific IgE by Immuno-CAP FEIA, skin testing, basophil activation experiments by flow-assisted determination of CD63 expression in the patient and 3 healthy controls. Immuno-CAP inhibition experiments were applied to investigate cross-reactivity.</AbstractText>
                <AbstractText Label="RESULTS" NlmCategory="RESULTS">Specific IgE, skin tests and basophil activation tests were clearly positive in the patient, whereas they remained negative in controls. No cross-reactivity between fenugreek and coriander was demonstrable by inhibition experiments.</AbstractText>
                <AbstractText Label="CONCLUSIONS" NlmCategory="CONCLUSIONS">The clinical manifestations in temporal relationship to ingestion of coriander and handling of coriander and/or fenugreek, the positive specific IgE results, skin tests and basophil activation assays support the diagnosis of allergy to both spices. History suggests sensitization by occupational exposure.</AbstractText>
            </Abstract>
            <AuthorList CompleteYN="Y">
                <Author ValidYN="Y">
                    <LastName>Ebo</LastName>
                    <ForeName>D G</ForeName>
                    <Initials>DG</Initials>
                    <Affiliation>Dept. Immunology-Allergology-Rheumatology, University Antwerpen.</Affiliation>
                </Author>
                <Author ValidYN="Y">
                    <LastName>Bridts</LastName>
                    <ForeName>C H</ForeName>
                    <Initials>CH</Initials>
                </Author>
                <Author ValidYN="Y">
                    <LastName>Mertens</LastName>
                    <ForeName>M H</ForeName>
                    <Initials>MH</Initials>
                </Author>
                <Author ValidYN="Y">
                    <LastName>Stevens</LastName>
                    <ForeName>W J</ForeName>
                    <Initials>WJ</Initials>
                </Author>
            </AuthorList>
            <Language>eng</Language>
            <PublicationTypeList>
                <PublicationType>Case Reports</PublicationType>
                <PublicationType>Journal Article</PublicationType>
            </PublicationTypeList>
        </Article>
        <MedlineJournalInfo>
            <Country>Belgium</Country>
            <MedlineTA>Acta Clin Belg</MedlineTA>
            <NlmUniqueID>0370306</NlmUniqueID>
        </MedlineJournalInfo>
        <ChemicalList>
            <Chemical>
                <RegistryNumber>37341-29-0</RegistryNumber>
                <NameOfSubstance>Immunoglobulin E</NameOfSubstance>
            </Chemical>
        </ChemicalList>
        <CitationSubset>IM</CitationSubset>
        <MeshHeadingList>
            <MeshHeading>
                <DescriptorName MajorTopicYN="N">Adult</DescriptorName>
            </MeshHeading>
            <MeshHeading>
                <DescriptorName MajorTopicYN="N">Anaphylaxis</DescriptorName>
                <QualifierName MajorTopicYN="N">blood</QualifierName>
                <QualifierName MajorTopicYN="Y">chemically induced</QualifierName>
                <QualifierName MajorTopicYN="N">diagnosis</QualifierName>
            </MeshHeading>
            <MeshHeading>
                <DescriptorName MajorTopicYN="N">Coriandrum</DescriptorName>
                <QualifierName MajorTopicYN="Y">adverse effects</QualifierName>
            </MeshHeading>
            <MeshHeading>
                <DescriptorName MajorTopicYN="N">Diagnosis, Differential</DescriptorName>
            </MeshHeading>
            <MeshHeading>
                <DescriptorName MajorTopicYN="N">Humans</DescriptorName>
            </MeshHeading>
            <MeshHeading>
                <DescriptorName MajorTopicYN="N">Immunoglobulin E</DescriptorName>
                <QualifierName MajorTopicYN="N">blood</QualifierName>
            </MeshHeading>
            <MeshHeading>
                <DescriptorName MajorTopicYN="N">Male</DescriptorName>
            </MeshHeading>
            <MeshHeading>
                <DescriptorName MajorTopicYN="N">Occupational Diseases</DescriptorName>
                <QualifierName MajorTopicYN="N">blood</QualifierName>
                <QualifierName MajorTopicYN="Y">chemically induced</QualifierName>
                <QualifierName MajorTopicYN="N">diagnosis</QualifierName>
            </MeshHeading>
            <MeshHeading>
                <DescriptorName MajorTopicYN="N">Occupational Exposure</DescriptorName>
                <QualifierName MajorTopicYN="Y">adverse effects</QualifierName>
            </MeshHeading>
            <MeshHeading>
                <DescriptorName MajorTopicYN="N">Severity of Illness Index</DescriptorName>
            </MeshHeading>
            <MeshHeading>
                <DescriptorName MajorTopicYN="N">Skin Tests</DescriptorName>
            </MeshHeading>
            <MeshHeading>
                <DescriptorName MajorTopicYN="N">Spices</DescriptorName>
                <QualifierName MajorTopicYN="Y">adverse effects</QualifierName>
            </MeshHeading>
        </MeshHeadingList>
    </MedlineCitation>
    <PubmedData>
        <History>
            <PubMedPubDate PubStatus="pubmed">
                <Year>2006</Year>
                <Month>8</Month>
                <Day>3</Day>
                <Hour>9</Hour>
                <Minute>0</Minute>
            </PubMedPubDate>
            <PubMedPubDate PubStatus="medline">
                <Year>2006</Year>
                <Month>9</Month>
                <Day>13</Day>
                <Hour>9</Hour>
                <Minute>0</Minute>
            </PubMedPubDate>
            <PubMedPubDate PubStatus="entrez">
                <Year>2006</Year>
                <Month>8</Month>
                <Day>3</Day>
                <Hour>9</Hour>
                <Minute>0</Minute>
            </PubMedPubDate>
        </History>
        <PublicationStatus>ppublish</PublicationStatus>
        <ArticleIdList>
            <ArticleId IdType="pubmed">16881566</ArticleId>
            <ArticleId IdType="doi">10.1179/acb.2006.025</ArticleId>
        </ArticleIdList>
    </PubmedData>
</PubmedArticle>
