<PubmedArticle>
    <MedlineCitation Owner="NLM" Status="MEDLINE">
        <PMID Version="1">18034788</PMID>
        <DateCreated>
            <Year>2008</Year>
            <Month>01</Month>
            <Day>21</Day>
        </DateCreated>
        <DateCompleted>
            <Year>2008</Year>
            <Month>06</Month>
            <Day>16</Day>
        </DateCompleted>
        <DateRevised>
            <Year>2013</Year>
            <Month>11</Month>
            <Day>21</Day>
        </DateRevised>
        <Article PubModel="Print-Electronic">
            <Journal>
                <ISSN IssnType="Print">0042-9007</ISSN>
                <JournalIssue CitedMedium="Print">
                    <Volume>94</Volume>
                    <Issue>2</Issue>
                    <PubDate>
                        <Year>2008</Year>
                        <Month>Feb</Month>
                    </PubDate>
                </JournalIssue>
                <Title>Vox sanguinis</Title>
                <ISOAbbreviation>Vox Sang.</ISOAbbreviation>
            </Journal>
            <ArticleTitle>In vitro and in vivo effects of potassium and magnesium on storage up to 7 days of apheresis platelet concentrates in platelet additive solution.</ArticleTitle>
            <Pagination>
                <MedlinePgn>96-102</MedlinePgn>
            </Pagination>
            <Abstract>
                <AbstractText Label="BACKGROUND AND OBJECTIVE" NlmCategory="OBJECTIVE">Prolonged storage of platelets up to 7 days provides improved availability, logistical management and decreased wastage. Beside methods of bacterial detection, addition of magnesium and potassium to the platelet storage solution (SSP+) may further improve the quality of platelets with extended storage.</AbstractText>
                <AbstractText Label="MATERIALS AND METHODS" NlmCategory="METHODS">Apheresis platelets from 10 donors were divided and stored in two different platelet additive solutions (PAS) (Intersol and SSP+) for a paired comparison. A variety of in vitro platelet function and metabolic assays were performed both on day 1 and after 7 days of storage. For in vivo study, platelets were labelled with either (111)Indium or (51)Chromium after 7 days of storage and were injected into the corresponding donor. Serial blood samples were drawn for recovery and survival measurements.</AbstractText>
                <AbstractText Label="RESULTS" NlmCategory="RESULTS">In vitro parameters for SSP+ showed significantly reduced glycolysis (lower glucose consumption and decreased production of lactate), a higher hypotonic shock response (HSR) and the extent of shape change reactivity and a lower degree of platelet activation by means of RANTES (regulated on activation, normal, T cell-expressed, and secreted), CD62p and CD63 expression. Platelet recovery on day 7 was higher for Intersol as compared to SSP+, 65 +/- 11 vs. 53 +/- 13% (P = 0.023), and survival showed no difference 4.2 +/- 1.9 vs. 3.6 +/- 1.4 days.</AbstractText>
                <AbstractText Label="CONCLUSION" NlmCategory="CONCLUSIONS">In vitro characteristics of platelets stored in PAS with addition of potassium and magnesium indicated higher quality, but this could not be verified by the in vivo parameters by means of recovery and survival.</AbstractText>
            </Abstract>
            <AuthorList CompleteYN="Y">
                <Author ValidYN="Y">
                    <LastName>Diedrich</LastName>
                    <ForeName>B</ForeName>
                    <Initials>B</Initials>
                    <Affiliation>Department of Laboratory Medicine, Karolinska Institutet, Stockholm, Sweden. beatrice.diedrich@karolinska.se</Affiliation>
                </Author>
                <Author ValidYN="Y">
                    <LastName>Sandgren</LastName>
                    <ForeName>P</ForeName>
                    <Initials>P</Initials>
                </Author>
                <Author ValidYN="Y">
                    <LastName>Jansson</LastName>
                    <ForeName>B</ForeName>
                    <Initials>B</Initials>
                </Author>
                <Author ValidYN="Y">
                    <LastName>Gulliksson</LastName>
                    <ForeName>H</ForeName>
                    <Initials>H</Initials>
                </Author>
                <Author ValidYN="Y">
                    <LastName>Svensson</LastName>
                    <ForeName>L</ForeName>
                    <Initials>L</Initials>
                </Author>
                <Author ValidYN="Y">
                    <LastName>Shanwell</LastName>
                    <ForeName>A</ForeName>
                    <Initials>A</Initials>
                </Author>
            </AuthorList>
            <Language>eng</Language>
            <PublicationTypeList>
                <PublicationType>Journal Article</PublicationType>
                <PublicationType>Randomized Controlled Trial</PublicationType>
            </PublicationTypeList>
            <ArticleDate DateType="Electronic">
                <Year>2007</Year>
                <Month>11</Month>
                <Day>22</Day>
            </ArticleDate>
        </Article>
        <MedlineJournalInfo>
            <Country>England</Country>
            <MedlineTA>Vox Sang</MedlineTA>
            <NlmUniqueID>0413606</NlmUniqueID>
            <ISSNLinking>0042-9007</ISSNLinking>
        </MedlineJournalInfo>
        <ChemicalList>
            <Chemical>
                <RegistryNumber>0</RegistryNumber>
                <NameOfSubstance>Organ Preservation Solutions</NameOfSubstance>
            </Chemical>
            <Chemical>
                <RegistryNumber>0</RegistryNumber>
                <NameOfSubstance>Pharmaceutical Solutions</NameOfSubstance>
            </Chemical>
            <Chemical>
                <RegistryNumber>0</RegistryNumber>
                <NameOfSubstance>Radioisotopes</NameOfSubstance>
            </Chemical>
            <Chemical>
                <RegistryNumber>I38ZP9992A</RegistryNumber>
                <NameOfSubstance>Magnesium</NameOfSubstance>
            </Chemical>
            <Chemical>
                <RegistryNumber>RWP5GA015D</RegistryNumber>
                <NameOfSubstance>Potassium</NameOfSubstance>
            </Chemical>
        </ChemicalList>
        <CitationSubset>IM</CitationSubset>
        <MeshHeadingList>
            <MeshHeading>
                <DescriptorName MajorTopicYN="N">Blood Platelets</DescriptorName>
                <QualifierName MajorTopicYN="Y">cytology</QualifierName>
            </MeshHeading>
            <MeshHeading>
                <DescriptorName MajorTopicYN="N">Blood Preservation</DescriptorName>
                <QualifierName MajorTopicYN="Y">methods</QualifierName>
            </MeshHeading>
            <MeshHeading>
                <DescriptorName MajorTopicYN="N">Cell Physiological Phenomena</DescriptorName>
            </MeshHeading>
            <MeshHeading>
                <DescriptorName MajorTopicYN="N">Cell Survival</DescriptorName>
            </MeshHeading>
            <MeshHeading>
                <DescriptorName MajorTopicYN="N">Humans</DescriptorName>
            </MeshHeading>
            <MeshHeading>
                <DescriptorName MajorTopicYN="N">Magnesium</DescriptorName>
                <QualifierName MajorTopicYN="Y">pharmacology</QualifierName>
            </MeshHeading>
            <MeshHeading>
                <DescriptorName MajorTopicYN="N">Organ Preservation Solutions</DescriptorName>
                <QualifierName MajorTopicYN="N">chemistry</QualifierName>
                <QualifierName MajorTopicYN="N">pharmacology</QualifierName>
            </MeshHeading>
            <MeshHeading>
                <DescriptorName MajorTopicYN="N">Pharmaceutical Solutions</DescriptorName>
                <QualifierName MajorTopicYN="N">chemistry</QualifierName>
                <QualifierName MajorTopicYN="N">pharmacology</QualifierName>
            </MeshHeading>
            <MeshHeading>
                <DescriptorName MajorTopicYN="N">Platelet Transfusion</DescriptorName>
                <QualifierName MajorTopicYN="N">methods</QualifierName>
                <QualifierName MajorTopicYN="Y">standards</QualifierName>
            </MeshHeading>
            <MeshHeading>
                <DescriptorName MajorTopicYN="N">Plateletpheresis</DescriptorName>
            </MeshHeading>
            <MeshHeading>
                <DescriptorName MajorTopicYN="N">Potassium</DescriptorName>
                <QualifierName MajorTopicYN="Y">pharmacology</QualifierName>
            </MeshHeading>
            <MeshHeading>
                <DescriptorName MajorTopicYN="N">Radioisotopes</DescriptorName>
            </MeshHeading>
            <MeshHeading>
                <DescriptorName MajorTopicYN="N">Time Factors</DescriptorName>
            </MeshHeading>
        </MeshHeadingList>
    </MedlineCitation>
    <PubmedData>
        <History>
            <PubMedPubDate PubStatus="aheadofprint">
                <Year>2007</Year>
                <Month>11</Month>
                <Day>22</Day>
            </PubMedPubDate>
            <PubMedPubDate PubStatus="pubmed">
                <Year>2007</Year>
                <Month>11</Month>
                <Day>24</Day>
                <Hour>9</Hour>
                <Minute>0</Minute>
            </PubMedPubDate>
            <PubMedPubDate PubStatus="medline">
                <Year>2008</Year>
                <Month>6</Month>
                <Day>17</Day>
                <Hour>9</Hour>
                <Minute>0</Minute>
            </PubMedPubDate>
            <PubMedPubDate PubStatus="entrez">
                <Year>2007</Year>
                <Month>11</Month>
                <Day>24</Day>
                <Hour>9</Hour>
                <Minute>0</Minute>
            </PubMedPubDate>
        </History>
        <PublicationStatus>ppublish</PublicationStatus>
        <ArticleIdList>
            <ArticleId IdType="pii">VOX1002</ArticleId>
            <ArticleId IdType="doi">10.1111/j.1423-0410.2007.01002.x</ArticleId>
            <ArticleId IdType="pubmed">18034788</ArticleId>
        </ArticleIdList>
    </PubmedData>
</PubmedArticle>
