<PubmedArticle>
    <MedlineCitation Owner="NLM" Status="MEDLINE">
        <PMID Version="1">19233449</PMID>
        <DateCreated>
            <Year>2009</Year>
            <Month>06</Month>
            <Day>01</Day>
        </DateCreated>
        <DateCompleted>
            <Year>2009</Year>
            <Month>09</Month>
            <Day>24</Day>
        </DateCompleted>
        <DateRevised>
            <Year>2013</Year>
            <Month>11</Month>
            <Day>21</Day>
        </DateRevised>
        <Article PubModel="Print-Electronic">
            <Journal>
                <ISSN IssnType="Electronic">1879-2472</ISSN>
                <JournalIssue CitedMedium="Internet">
                    <Volume>124</Volume>
                    <Issue>2</Issue>
                    <PubDate>
                        <Year>2009</Year>
                        <Month>Jun</Month>
                    </PubDate>
                </JournalIssue>
                <Title>Thrombosis research</Title>
                <ISOAbbreviation>Thromb. Res.</ISOAbbreviation>
            </Journal>
            <ArticleTitle>Levels and value of platelet activation markers in different subtypes of acute non-cardio-embolic ischemic stroke.</ArticleTitle>
            <Pagination>
                <MedlinePgn>213-8</MedlinePgn>
            </Pagination>
            <ELocationID EIdType="doi" ValidYN="Y">10.1016/j.thromres.2009.01.012</ELocationID>
            <Abstract>
                <AbstractText Label="INTRODUCTION" NlmCategory="BACKGROUND">Platelet activation and its interaction with leukocytes are important in the pathophysiology of ischemic stroke. This study aimed to evaluate the value of platelet activation and platelet-leukocyte interaction in different subtypes of acute, non-cardio-embolic ischemic stroke.</AbstractText>
                <AbstractText Label="METHODS" NlmCategory="METHODS">Fifty-four patients with acute, non-cardio-embolic ischemic stroke, including 32 small-vessel and 22 large-vessel diseases, were evaluated. Platelet activation markers (CD62P, CD63, and CD40L) and platelet-leukocyte interaction were measured by flow cytometry at different time points (&lt;48 hours and Days 7, 30, and 90 post-ischemic stroke). Markers were also evaluated in 28 other stroke patients in the convalescent stage (3 to 9 months after acute stroke) and in 28 control subjects.</AbstractText>
                <AbstractText Label="RESULTS" NlmCategory="RESULTS">Patients with ischemic stroke had significantly increased circulating CD62P, CD63, platelet-monocyte interaction, and platelet-lymphocyte interaction in the acute stage compared with the convalescent stage and control groups. Levels of CD62P and CD63 were significantly higher in the large-vessel disease group than in the small-vessel disease group, and differences in CD62P were significant even at one month. The CD40L level in the poor outcome group was significantly higher than that in the good outcome group. Stroke patients with diabetes mellitus and large-vessel disease were associated with poor outcome.</AbstractText>
                <AbstractText Label="CONCLUSIONS" NlmCategory="CONCLUSIONS">Patients with large-vessel cerebral infarction elicit higher platelet activation and platelet-leukocyte interaction compared to small-vessel infarction. Further large scale trials are warranted to evaluate the relationship between platelet activation markers and outcome in stroke patients under different anti-platelet therapies, and to clarify optimal treatment.</AbstractText>
            </Abstract>
            <AuthorList CompleteYN="Y">
                <Author ValidYN="Y">
                    <LastName>Tsai</LastName>
                    <ForeName>Nai-Wen</ForeName>
                    <Initials>NW</Initials>
                    <Affiliation>Department of Neurology, Chang Gung Memorial Hospital-Kaohsiung Medical Center, Chang Gung University College of Medicine, Kaohsiung, Taiwan.</Affiliation>
                </Author>
                <Author ValidYN="Y">
                    <LastName>Chang</LastName>
                    <ForeName>Wen-Neng</ForeName>
                    <Initials>WN</Initials>
                </Author>
                <Author ValidYN="Y">
                    <LastName>Shaw</LastName>
                    <ForeName>Chen-Fu</ForeName>
                    <Initials>CF</Initials>
                </Author>
                <Author ValidYN="Y">
                    <LastName>Jan</LastName>
                    <ForeName>Chung-Ren</ForeName>
                    <Initials>CR</Initials>
                </Author>
                <Author ValidYN="Y">
                    <LastName>Chang</LastName>
                    <ForeName>Hsueh-Wen</ForeName>
                    <Initials>HW</Initials>
                </Author>
                <Author ValidYN="Y">
                    <LastName>Huang</LastName>
                    <ForeName>Chi-Ren</ForeName>
                    <Initials>CR</Initials>
                </Author>
                <Author ValidYN="Y">
                    <LastName>Chen</LastName>
                    <ForeName>Shang-Der</ForeName>
                    <Initials>SD</Initials>
                </Author>
                <Author ValidYN="Y">
                    <LastName>Chuang</LastName>
                    <ForeName>Yao-Chung</ForeName>
                    <Initials>YC</Initials>
                </Author>
                <Author ValidYN="Y">
                    <LastName>Lee</LastName>
                    <ForeName>Lian-Hui</ForeName>
                    <Initials>LH</Initials>
                </Author>
                <Author ValidYN="Y">
                    <LastName>Wang</LastName>
                    <ForeName>Hung-Chen</ForeName>
                    <Initials>HC</Initials>
                </Author>
                <Author ValidYN="Y">
                    <LastName>Lee</LastName>
                    <ForeName>Tsong-Hai</ForeName>
                    <Initials>TH</Initials>
                </Author>
                <Author ValidYN="Y">
                    <LastName>Lu</LastName>
                    <ForeName>Cheng-Hsien</ForeName>
                    <Initials>CH</Initials>
                </Author>
            </AuthorList>
            <Language>eng</Language>
            <PublicationTypeList>
                <PublicationType>Journal Article</PublicationType>
                <PublicationType>Research Support, Non-U.S. Gov't</PublicationType>
            </PublicationTypeList>
            <ArticleDate DateType="Electronic">
                <Year>2009</Year>
                <Month>02</Month>
                <Day>23</Day>
            </ArticleDate>
        </Article>
        <MedlineJournalInfo>
            <Country>United States</Country>
            <MedlineTA>Thromb Res</MedlineTA>
            <NlmUniqueID>0326377</NlmUniqueID>
            <ISSNLinking>0049-3848</ISSNLinking>
        </MedlineJournalInfo>
        <ChemicalList>
            <Chemical>
                <RegistryNumber>0</RegistryNumber>
                <NameOfSubstance>Antibodies</NameOfSubstance>
            </Chemical>
            <Chemical>
                <RegistryNumber>0</RegistryNumber>
                <NameOfSubstance>Antigens, CD</NameOfSubstance>
            </Chemical>
            <Chemical>
                <RegistryNumber>0</RegistryNumber>
                <NameOfSubstance>Biological Markers</NameOfSubstance>
            </Chemical>
            <Chemical>
                <RegistryNumber>0</RegistryNumber>
                <NameOfSubstance>Fluorescent Dyes</NameOfSubstance>
            </Chemical>
            <Chemical>
                <RegistryNumber>0</RegistryNumber>
                <NameOfSubstance>P-Selectin</NameOfSubstance>
            </Chemical>
            <Chemical>
                <RegistryNumber>0</RegistryNumber>
                <NameOfSubstance>Platelet Membrane Glycoproteins</NameOfSubstance>
            </Chemical>
            <Chemical>
                <RegistryNumber>11016-17-4</RegistryNumber>
                <NameOfSubstance>Phycoerythrin</NameOfSubstance>
            </Chemical>
            <Chemical>
                <RegistryNumber>EC 3.1.3.48</RegistryNumber>
                <NameOfSubstance>Antigens, CD45</NameOfSubstance>
            </Chemical>
            <Chemical>
                <RegistryNumber>I223NX31W9</RegistryNumber>
                <NameOfSubstance>Fluorescein-5-isothiocyanate</NameOfSubstance>
            </Chemical>
        </ChemicalList>
        <CitationSubset>IM</CitationSubset>
        <MeshHeadingList>
            <MeshHeading>
                <DescriptorName MajorTopicYN="N">Acute Disease</DescriptorName>
            </MeshHeading>
            <MeshHeading>
                <DescriptorName MajorTopicYN="N">Aged</DescriptorName>
            </MeshHeading>
            <MeshHeading>
                <DescriptorName MajorTopicYN="N">Antibodies</DescriptorName>
                <QualifierName MajorTopicYN="N">metabolism</QualifierName>
            </MeshHeading>
            <MeshHeading>
                <DescriptorName MajorTopicYN="N">Antigens, CD</DescriptorName>
                <QualifierName MajorTopicYN="N">blood</QualifierName>
                <QualifierName MajorTopicYN="N">metabolism</QualifierName>
            </MeshHeading>
            <MeshHeading>
                <DescriptorName MajorTopicYN="N">Antigens, CD45</DescriptorName>
                <QualifierName MajorTopicYN="N">metabolism</QualifierName>
            </MeshHeading>
            <MeshHeading>
                <DescriptorName MajorTopicYN="N">Biological Markers</DescriptorName>
                <QualifierName MajorTopicYN="N">blood</QualifierName>
            </MeshHeading>
            <MeshHeading>
                <DescriptorName MajorTopicYN="N">Blood Platelets</DescriptorName>
                <QualifierName MajorTopicYN="Y">metabolism</QualifierName>
            </MeshHeading>
            <MeshHeading>
                <DescriptorName MajorTopicYN="N">Brain Ischemia</DescriptorName>
                <QualifierName MajorTopicYN="N">complications</QualifierName>
                <QualifierName MajorTopicYN="Y">metabolism</QualifierName>
            </MeshHeading>
            <MeshHeading>
                <DescriptorName MajorTopicYN="N">Case-Control Studies</DescriptorName>
            </MeshHeading>
            <MeshHeading>
                <DescriptorName MajorTopicYN="N">Female</DescriptorName>
            </MeshHeading>
            <MeshHeading>
                <DescriptorName MajorTopicYN="N">Fluorescein-5-isothiocyanate</DescriptorName>
                <QualifierName MajorTopicYN="N">metabolism</QualifierName>
            </MeshHeading>
            <MeshHeading>
                <DescriptorName MajorTopicYN="N">Fluorescent Dyes</DescriptorName>
                <QualifierName MajorTopicYN="N">metabolism</QualifierName>
            </MeshHeading>
            <MeshHeading>
                <DescriptorName MajorTopicYN="N">Humans</DescriptorName>
            </MeshHeading>
            <MeshHeading>
                <DescriptorName MajorTopicYN="N">Leukocytes</DescriptorName>
                <QualifierName MajorTopicYN="N">metabolism</QualifierName>
            </MeshHeading>
            <MeshHeading>
                <DescriptorName MajorTopicYN="N">Male</DescriptorName>
            </MeshHeading>
            <MeshHeading>
                <DescriptorName MajorTopicYN="N">Middle Aged</DescriptorName>
            </MeshHeading>
            <MeshHeading>
                <DescriptorName MajorTopicYN="N">P-Selectin</DescriptorName>
                <QualifierName MajorTopicYN="N">blood</QualifierName>
                <QualifierName MajorTopicYN="N">metabolism</QualifierName>
            </MeshHeading>
            <MeshHeading>
                <DescriptorName MajorTopicYN="N">Phycoerythrin</DescriptorName>
                <QualifierName MajorTopicYN="N">metabolism</QualifierName>
            </MeshHeading>
            <MeshHeading>
                <DescriptorName MajorTopicYN="N">Platelet Activation</DescriptorName>
                <QualifierName MajorTopicYN="Y">physiology</QualifierName>
            </MeshHeading>
            <MeshHeading>
                <DescriptorName MajorTopicYN="N">Platelet Function Tests</DescriptorName>
            </MeshHeading>
            <MeshHeading>
                <DescriptorName MajorTopicYN="N">Platelet Membrane Glycoproteins</DescriptorName>
                <QualifierName MajorTopicYN="N">metabolism</QualifierName>
            </MeshHeading>
            <MeshHeading>
                <DescriptorName MajorTopicYN="N">Stroke</DescriptorName>
                <QualifierName MajorTopicYN="N">complications</QualifierName>
                <QualifierName MajorTopicYN="Y">metabolism</QualifierName>
            </MeshHeading>
        </MeshHeadingList>
    </MedlineCitation>
    <PubmedData>
        <History>
            <PubMedPubDate PubStatus="received">
                <Year>2008</Year>
                <Month>8</Month>
                <Day>29</Day>
            </PubMedPubDate>
            <PubMedPubDate PubStatus="revised">
                <Year>2008</Year>
                <Month>12</Month>
                <Day>24</Day>
            </PubMedPubDate>
            <PubMedPubDate PubStatus="accepted">
                <Year>2009</Year>
                <Month>1</Month>
                <Day>21</Day>
            </PubMedPubDate>
            <PubMedPubDate PubStatus="aheadofprint">
                <Year>2009</Year>
                <Month>2</Month>
                <Day>23</Day>
            </PubMedPubDate>
            <PubMedPubDate PubStatus="entrez">
                <Year>2009</Year>
                <Month>2</Month>
                <Day>24</Day>
                <Hour>9</Hour>
                <Minute>0</Minute>
            </PubMedPubDate>
            <PubMedPubDate PubStatus="pubmed">
                <Year>2009</Year>
                <Month>2</Month>
                <Day>24</Day>
                <Hour>9</Hour>
                <Minute>0</Minute>
            </PubMedPubDate>
            <PubMedPubDate PubStatus="medline">
                <Year>2009</Year>
                <Month>9</Month>
                <Day>25</Day>
                <Hour>6</Hour>
                <Minute>0</Minute>
            </PubMedPubDate>
        </History>
        <PublicationStatus>ppublish</PublicationStatus>
        <ArticleIdList>
            <ArticleId IdType="pii">S0049-3848(09)00064-4</ArticleId>
            <ArticleId IdType="doi">10.1016/j.thromres.2009.01.012</ArticleId>
            <ArticleId IdType="pubmed">19233449</ArticleId>
        </ArticleIdList>
    </PubmedData>
</PubmedArticle>
