<PubmedArticle>
    <MedlineCitation Owner="NLM" Status="MEDLINE">
        <PMID Version="1">20801889</PMID>
        <DateCreated>
            <Year>2010</Year>
            <Month>11</Month>
            <Day>01</Day>
        </DateCreated>
        <DateCompleted>
            <Year>2010</Year>
            <Month>11</Month>
            <Day>30</Day>
        </DateCompleted>
        <DateRevised>
            <Year>2013</Year>
            <Month>10</Month>
            <Day>23</Day>
        </DateRevised>
        <Article PubModel="Print-Electronic">
            <Journal>
                <ISSN IssnType="Electronic">1083-351X</ISSN>
                <JournalIssue CitedMedium="Internet">
                    <Volume>285</Volume>
                    <Issue>45</Issue>
                    <PubDate>
                        <Year>2010</Year>
                        <Month>Nov</Month>
                        <Day>5</Day>
                    </PubDate>
                </JournalIssue>
                <Title>The Journal of biological chemistry</Title>
                <ISOAbbreviation>J. Biol. Chem.</ISOAbbreviation>
            </Journal>
            <ArticleTitle>Selective fusion of azurophilic granules with Leishmania-containing phagosomes in human neutrophils.</ArticleTitle>
            <Pagination>
                <MedlinePgn>34528-36</MedlinePgn>
            </Pagination>
            <ELocationID EIdType="doi" ValidYN="Y">10.1074/jbc.M110.125302</ELocationID>
            <Abstract>
                <AbstractText>Leishmania parasites use polymorphonuclear neutrophils as intermediate hosts before their ultimate delivery to macrophages following engulfment of parasite-infected neutrophils. This leads to a silent and unrecognized entry of Leishmania into the macrophage host cell. Neutrophil function depends on its cytoplasmic granules, but their mobilization and role in how Leishmania parasites evade intracellular killing in neutrophils remain undetermined. Here, we have found by ultrastructural approaches that neutrophils ingested Leishmania major promastigotes, and azurophilic granules fused in a preferential way with parasite-containing phagosomes, without promoting parasite killing. Azurophilic granules, identified by the granule marker myeloperoxidase, also fused with Leishmania donovani-engulfed vacuoles in human neutrophils. In addition, the azurophilic membrane marker CD63 was also detected in the vacuole surrounding the parasite, and in the fusion of azurophilic granules with the parasite-engulfed phagosome. Tertiary and specific granules, involved in vacuole acidification and superoxide anion generation, hardly fused with Leishmania-containing phagosomes. L. major interaction with neutrophils did not elicit production of reactive oxygen species or mobilization of tertiary and specific granules. By using immunogold electron microscopy approaches in the engulfment of L. major and L. donovani by human neutrophils, we did not find a significant contribution of endoplasmic reticulum to the formation of Leishmania-containing vacuoles. Live Leishmania parasites were required to be optimally internalized by neutrophils. Our data suggest that Leishmania promastigotes modulate their uptake by neutrophils, and regulate granule fusion processes in a rather selective way to favor parasite survival in human neutrophils.</AbstractText>
            </Abstract>
            <AuthorList CompleteYN="Y">
                <Author ValidYN="Y">
                    <LastName>Mollinedo</LastName>
                    <ForeName>Faustino</ForeName>
                    <Initials>F</Initials>
                    <Affiliation>Instituto de Biología Molecular y Celular del Cáncer, Centro de Investigación del Cáncer, CSIC-Universidad de Salamanca, Campus Miguel de Unamuno, E-37007 Salamanca, Spain. fmollin@usal.es</Affiliation>
                </Author>
                <Author ValidYN="Y">
                    <LastName>Janssen</LastName>
                    <ForeName>Hans</ForeName>
                    <Initials>H</Initials>
                </Author>
                <Author ValidYN="Y">
                    <LastName>de la Iglesia-Vicente</LastName>
                    <ForeName>Janis</ForeName>
                    <Initials>J</Initials>
                </Author>
                <Author ValidYN="Y">
                    <LastName>Villa-Pulgarin</LastName>
                    <ForeName>Janny A</ForeName>
                    <Initials>JA</Initials>
                </Author>
                <Author ValidYN="Y">
                    <LastName>Calafat</LastName>
                    <ForeName>Jero</ForeName>
                    <Initials>J</Initials>
                </Author>
            </AuthorList>
            <Language>eng</Language>
            <PublicationTypeList>
                <PublicationType>Journal Article</PublicationType>
                <PublicationType>Research Support, Non-U.S. Gov't</PublicationType>
            </PublicationTypeList>
            <ArticleDate DateType="Electronic">
                <Year>2010</Year>
                <Month>08</Month>
                <Day>26</Day>
            </ArticleDate>
        </Article>
        <MedlineJournalInfo>
            <Country>United States</Country>
            <MedlineTA>J Biol Chem</MedlineTA>
            <NlmUniqueID>2985121R</NlmUniqueID>
            <ISSNLinking>0021-9258</ISSNLinking>
        </MedlineJournalInfo>
        <CitationSubset>IM</CitationSubset>
        <CommentsCorrectionsList>
            <CommentsCorrections RefType="Cites">
                <RefSource>Biochem Biophys Res Commun. 1988 Jul 29;154(2):641-7</RefSource>
                <PMID Version="1">3135806</PMID>
            </CommentsCorrections>
            <CommentsCorrections RefType="Cites">
                <RefSource>J Cell Biol. 1971 Oct;51(1):193-215</RefSource>
                <PMID Version="1">4329520</PMID>
            </CommentsCorrections>
            <CommentsCorrections RefType="Cites">
                <RefSource>J Med Microbiol. 1990 Jul;32(3):189-93</RefSource>
                <PMID Version="1">2374156</PMID>
            </CommentsCorrections>
            <CommentsCorrections RefType="Cites">
                <RefSource>Parasite Immunol. 1990 May;12(3):285-95</RefSource>
                <PMID Version="1">2385444</PMID>
            </CommentsCorrections>
            <CommentsCorrections RefType="Cites">
                <RefSource>Scand J Immunol. 1991 Jul;34(1):33-43</RefSource>
                <PMID Version="1">1676856</PMID>
            </CommentsCorrections>
            <CommentsCorrections RefType="Cites">
                <RefSource>Blood. 1991 Aug 15;78(4):1105-11</RefSource>
                <PMID Version="1">1907873</PMID>
            </CommentsCorrections>
            <CommentsCorrections RefType="Cites">
                <RefSource>Mol Cell Biochem. 1991 Jun 26;105(1):49-60</RefSource>
                <PMID Version="1">1656202</PMID>
            </CommentsCorrections>
            <CommentsCorrections RefType="Cites">
                <RefSource>J Immunol. 1981 Oct;127(4):1438-43</RefSource>
                <PMID Version="1">7276565</PMID>
            </CommentsCorrections>
            <CommentsCorrections RefType="Cites">
                <RefSource>J Histochem Cytochem. 1984 Feb;32(2):165-71</RefSource>
                <PMID Version="1">6319482</PMID>
            </CommentsCorrections>
            <CommentsCorrections RefType="Cites">
                <RefSource>J Biol Chem. 1984 Jun 10;259(11):7143-50</RefSource>
                <PMID Version="1">6144682</PMID>
            </CommentsCorrections>
            <CommentsCorrections RefType="Cites">
                <RefSource>J Biol Chem. 1986 Jan 25;261(3):1077-82</RefSource>
                <PMID Version="1">3003052</PMID>
            </CommentsCorrections>
            <CommentsCorrections RefType="Cites">
                <RefSource>J Immunol. 1986 Jun 1;136(11):4220-5</RefSource>
                <PMID Version="1">3009619</PMID>
            </CommentsCorrections>
            <CommentsCorrections RefType="Cites">
                <RefSource>FEBS Lett. 1987 Jun 15;217(2):158-62</RefSource>
                <PMID Version="1">3036578</PMID>
            </CommentsCorrections>
            <CommentsCorrections RefType="Cites">
                <RefSource>J Med Microbiol. 1988 Feb;25(2):101-7</RefSource>
                <PMID Version="1">3276896</PMID>
            </CommentsCorrections>
            <CommentsCorrections RefType="Cites">
                <RefSource>J Biol Chem. 1988 Jul 15;263(20):9946-51</RefSource>
                <PMID Version="1">2838485</PMID>
            </CommentsCorrections>
            <CommentsCorrections RefType="Cites">
                <RefSource>J Biol Chem. 1992 Feb 25;267(6):3553-6</RefSource>
                <PMID Version="1">1740407</PMID>
            </CommentsCorrections>
            <CommentsCorrections RefType="Cites">
                <RefSource>J Immunol. 1992 Jul 1;149(1):323-30</RefSource>
                <PMID Version="1">1607660</PMID>
            </CommentsCorrections>
            <CommentsCorrections RefType="Cites">
                <RefSource>Eur J Haematol. 1992 Oct;49(4):180-91</RefSource>
                <PMID Version="1">1464361</PMID>
            </CommentsCorrections>
            <CommentsCorrections RefType="Cites">
                <RefSource>J Biol Chem. 1995 Mar 3;270(9):4741-7</RefSource>
                <PMID Version="1">7876246</PMID>
            </CommentsCorrections>
            <CommentsCorrections RefType="Cites">
                <RefSource>J Immunol. 1995 Aug 15;155(4):2175-84</RefSource>
                <PMID Version="1">7636266</PMID>
            </CommentsCorrections>
            <CommentsCorrections RefType="Cites">
                <RefSource>Blood. 1997 May 15;89(10):3503-21</RefSource>
                <PMID Version="1">9160655</PMID>
            </CommentsCorrections>
            <CommentsCorrections RefType="Cites">
                <RefSource>J Immunol. 1997 Jul 1;159(1):409-18</RefSource>
                <PMID Version="1">9200480</PMID>
            </CommentsCorrections>
            <CommentsCorrections RefType="Cites">
                <RefSource>Blood. 1997 Aug 1;90(3):1255-66</RefSource>
                <PMID Version="1">9242560</PMID>
            </CommentsCorrections>
            <CommentsCorrections RefType="Cites">
                <RefSource>Biochem J. 1997 Nov 1;327 ( Pt 3):917-23</RefSource>
                <PMID Version="1">9581574</PMID>
            </CommentsCorrections>
            <CommentsCorrections RefType="Cites">
                <RefSource>Placenta. 1999 Mar-Apr;20(2-3):185-8</RefSource>
                <PMID Version="1">10195740</PMID>
            </CommentsCorrections>
            <CommentsCorrections RefType="Cites">
                <RefSource>J Immunol. 2004 Dec 1;173(11):6521-5</RefSource>
                <PMID Version="1">15557140</PMID>
            </CommentsCorrections>
            <CommentsCorrections RefType="Cites">
                <RefSource>Blood. 2005 Mar 15;105(6):2549-56</RefSource>
                <PMID Version="1">15546957</PMID>
            </CommentsCorrections>
            <CommentsCorrections RefType="Cites">
                <RefSource>Cell. 2005 Oct 7;123(1):157-70</RefSource>
                <PMID Version="1">16213220</PMID>
            </CommentsCorrections>
            <CommentsCorrections RefType="Cites">
                <RefSource>Cell Microbiol. 2006 Apr;8(4):690-703</RefSource>
                <PMID Version="1">16548894</PMID>
            </CommentsCorrections>
            <CommentsCorrections RefType="Cites">
                <RefSource>J Immunol. 2006 Sep 1;177(5):2831-41</RefSource>
                <PMID Version="1">16920918</PMID>
            </CommentsCorrections>
            <CommentsCorrections RefType="Cites">
                <RefSource>Eur J Immunol. 2006 Oct;36(10):2735-44</RefSource>
                <PMID Version="1">16955522</PMID>
            </CommentsCorrections>
            <CommentsCorrections RefType="Cites">
                <RefSource>Cell Microbiol. 2006 Dec;8(12):1922-31</RefSource>
                <PMID Version="1">16848789</PMID>
            </CommentsCorrections>
            <CommentsCorrections RefType="Cites">
                <RefSource>Cell Microbiol. 2008 Jan;10(1):100-11</RefSource>
                <PMID Version="1">17651446</PMID>
            </CommentsCorrections>
            <CommentsCorrections RefType="Cites">
                <RefSource>Science. 2008 Aug 15;321(5891):970-4</RefSource>
                <PMID Version="1">18703742</PMID>
            </CommentsCorrections>
            <CommentsCorrections RefType="Cites">
                <RefSource>Exp Parasitol. 2009 Jun;122(2):134-9</RefSource>
                <PMID Version="1">19303871</PMID>
            </CommentsCorrections>
            <CommentsCorrections RefType="Cites">
                <RefSource>J Immunol. 2009 Sep 15;183(6):3690-9</RefSource>
                <PMID Version="1">19710472</PMID>
            </CommentsCorrections>
            <CommentsCorrections RefType="Cites">
                <RefSource>Immunol Today. 1999 Dec;20(12):535-7</RefSource>
                <PMID Version="1">10636641</PMID>
            </CommentsCorrections>
            <CommentsCorrections RefType="Cites">
                <RefSource>Int J Cancer. 2000 Apr 15;86(2):208-18</RefSource>
                <PMID Version="1">10738248</PMID>
            </CommentsCorrections>
            <CommentsCorrections RefType="Cites">
                <RefSource>J Leukoc Biol. 2000 May;67(5):712-24</RefSource>
                <PMID Version="1">10811013</PMID>
            </CommentsCorrections>
            <CommentsCorrections RefType="Cites">
                <RefSource>Blood. 2000 Oct 1;96(7):2574-83</RefSource>
                <PMID Version="1">11001914</PMID>
            </CommentsCorrections>
            <CommentsCorrections RefType="Cites">
                <RefSource>J Exp Med. 2001 Mar 19;193(6):777-84</RefSource>
                <PMID Version="1">11257143</PMID>
            </CommentsCorrections>
            <CommentsCorrections RefType="Cites">
                <RefSource>Med Microbiol Immunol. 2001 Nov;190(1-2):73-6</RefSource>
                <PMID Version="1">11770115</PMID>
            </CommentsCorrections>
            <CommentsCorrections RefType="Cites">
                <RefSource>Cell. 2002 Jul 12;110(1):119-31</RefSource>
                <PMID Version="1">12151002</PMID>
            </CommentsCorrections>
            <CommentsCorrections RefType="Cites">
                <RefSource>J Immunol. 2003 Jan 15;170(2):1034-42</RefSource>
                <PMID Version="1">12517971</PMID>
            </CommentsCorrections>
            <CommentsCorrections RefType="Cites">
                <RefSource>Trends Microbiol. 2003 May;11(5):210-4</RefSource>
                <PMID Version="1">12781523</PMID>
            </CommentsCorrections>
            <CommentsCorrections RefType="Cites">
                <RefSource>Mol Pharmacol. 1989 Oct;36(4):547-55</RefSource>
                <PMID Version="1">2682203</PMID>
            </CommentsCorrections>
        </CommentsCorrectionsList>
        <MeshHeadingList>
            <MeshHeading>
                <DescriptorName MajorTopicYN="N">Animals</DescriptorName>
            </MeshHeading>
            <MeshHeading>
                <DescriptorName MajorTopicYN="N">Cytoplasmic Granules</DescriptorName>
                <QualifierName MajorTopicYN="Y">metabolism</QualifierName>
            </MeshHeading>
            <MeshHeading>
                <DescriptorName MajorTopicYN="N">Endoplasmic Reticulum</DescriptorName>
                <QualifierName MajorTopicYN="N">metabolism</QualifierName>
                <QualifierName MajorTopicYN="N">parasitology</QualifierName>
            </MeshHeading>
            <MeshHeading>
                <DescriptorName MajorTopicYN="N">Humans</DescriptorName>
            </MeshHeading>
            <MeshHeading>
                <DescriptorName MajorTopicYN="N">Leishmania donovani</DescriptorName>
                <QualifierName MajorTopicYN="Y">metabolism</QualifierName>
            </MeshHeading>
            <MeshHeading>
                <DescriptorName MajorTopicYN="N">Leishmania major</DescriptorName>
                <QualifierName MajorTopicYN="Y">metabolism</QualifierName>
            </MeshHeading>
            <MeshHeading>
                <DescriptorName MajorTopicYN="N">Leishmaniasis, Cutaneous</DescriptorName>
                <QualifierName MajorTopicYN="Y">metabolism</QualifierName>
            </MeshHeading>
            <MeshHeading>
                <DescriptorName MajorTopicYN="N">Leishmaniasis, Visceral</DescriptorName>
                <QualifierName MajorTopicYN="Y">metabolism</QualifierName>
            </MeshHeading>
            <MeshHeading>
                <DescriptorName MajorTopicYN="N">Membrane Fusion</DescriptorName>
            </MeshHeading>
            <MeshHeading>
                <DescriptorName MajorTopicYN="N">Neutrophils</DescriptorName>
                <QualifierName MajorTopicYN="Y">metabolism</QualifierName>
                <QualifierName MajorTopicYN="N">parasitology</QualifierName>
            </MeshHeading>
            <MeshHeading>
                <DescriptorName MajorTopicYN="N">Phagosomes</DescriptorName>
                <QualifierName MajorTopicYN="N">metabolism</QualifierName>
                <QualifierName MajorTopicYN="N">parasitology</QualifierName>
            </MeshHeading>
            <MeshHeading>
                <DescriptorName MajorTopicYN="N">Vacuoles</DescriptorName>
                <QualifierName MajorTopicYN="N">metabolism</QualifierName>
                <QualifierName MajorTopicYN="N">parasitology</QualifierName>
            </MeshHeading>
        </MeshHeadingList>
        <OtherID Source="NLM">PMC2966068</OtherID>
    </MedlineCitation>
    <PubmedData>
        <History>
            <PubMedPubDate PubStatus="aheadofprint">
                <Year>2010</Year>
                <Month>8</Month>
                <Day>26</Day>
            </PubMedPubDate>
            <PubMedPubDate PubStatus="entrez">
                <Year>2010</Year>
                <Month>8</Month>
                <Day>31</Day>
                <Hour>6</Hour>
                <Minute>0</Minute>
            </PubMedPubDate>
            <PubMedPubDate PubStatus="pubmed">
                <Year>2010</Year>
                <Month>8</Month>
                <Day>31</Day>
                <Hour>6</Hour>
                <Minute>0</Minute>
            </PubMedPubDate>
            <PubMedPubDate PubStatus="medline">
                <Year>2010</Year>
                <Month>12</Month>
                <Day>14</Day>
                <Hour>6</Hour>
                <Minute>0</Minute>
            </PubMedPubDate>
        </History>
        <PublicationStatus>ppublish</PublicationStatus>
        <ArticleIdList>
            <ArticleId IdType="pii">M110.125302</ArticleId>
            <ArticleId IdType="doi">10.1074/jbc.M110.125302</ArticleId>
            <ArticleId IdType="pubmed">20801889</ArticleId>
            <ArticleId IdType="pmc">PMC2966068</ArticleId>
        </ArticleIdList>
    </PubmedData>
</PubmedArticle>
